[
    {
        "question": "前進；通過；經過 (v.)",
        "answer": "pass"
    },
    {
        "question": "過去的；以前的；前任的 (adj.)；過去；昔日；往事 (n.)",
        "answer": "past"
    },
    {
        "question": "支付；付款給 (v.)；薪俸；報酬 (n.)",
        "answer": "pay"
    },
    {
        "question": "支付；付款 (n.)",
        "answer": "payment"
    },
    {
        "question": "筆；鋼筆 (n.)；寫作 (v.)",
        "answer": "pen"
    },
    {
        "question": "鉛筆 (n.)",
        "answer": "pencil"
    },
    {
        "question": "人們；民族 (n.)",
        "answer": "people"
    },
    {
        "question": "或許；可能 (adv.)",
        "answer": "perhaps"
    },
    {
        "question": "傢伙；外表；容貌 (n.)",
        "answer": "person"
    },
    {
        "question": "寵物 (n.)；把…當作寵兒 (v.)",
        "answer": "pet"
    },
    {
        "question": "鋼琴 (n.)",
        "answer": "piano"
    },
    {
        "question": "畫像；圖片；照片 (n.)",
        "answer": "picture"
    },
    {
        "question": "餡餅；派 (n.)",
        "answer": "pie"
    },
    {
        "question": "一個；一張；一片；一塊 (n.)",
        "answer": "piece"
    },
    {
        "question": "豬；小豬 (n.)",
        "answer": "pig"
    },
    {
        "question": "地方；地點；住所 (n.)",
        "answer": "place"
    },
    {
        "question": "計劃；方案 (n.)；計劃 (v.)",
        "answer": "plan"
    },
    {
        "question": "植物；農作物 (n.)；栽種；播種 (v.)",
        "answer": "plant"
    },
    {
        "question": "玩耍；戲弄；演奏 (v.)",
        "answer": "play"
    },
    {
        "question": "遊戲的人 (n.)",
        "answer": "player"
    },
    {
        "question": "操場；運動場 (n.)",
        "answer": "playground"
    },
    {
        "question": "請 (adv.)",
        "answer": "please"
    },
    {
        "question": "口袋 (n.)；把…裝入袋內 (v.)",
        "answer": "pocket"
    },
    {
        "question": "詩；詩歌；韻文 (n.)",
        "answer": "poetry"
    },
    {
        "question": "尖；尖端；尖頭 (n.)；指出；指明 (v.)",
        "answer": "point"
    },
    {
        "question": "警察；警方 (n.)",
        "answer": "police"
    },
    {
        "question": "警察；警員 (n.)",
        "answer": "policeman"
    },
    {
        "question": "池塘 (n.)；築堤造湖 (v.)",
        "answer": "pond"
    },
    {
        "question": "水塘；小水坑；潭 (n.)",
        "answer": "pool"
    },
    {
        "question": "貧窮的；粗劣的 (adj.)",
        "answer": "poor"
    },
    {
        "question": "位置；地點 (n.)",
        "answer": "position"
    },
    {
        "question": "可能的 (adj.)；可能（性） (n.)",
        "answer": "possible"
    },
    {
        "question": "政權；權力 (n.)；給…提供動力 (v.)",
        "answer": "power"
    },
    {
        "question": "準備；籌備 (v.)",
        "answer": "prepare"
    },
    {
        "question": "可愛的 (adj.)；相當；頗 (adv.)；漂亮的人；漂亮的東西 (n.)；使漂亮 (v.)",
        "answer": "pretty"
    },
    {
        "question": "價格；價錢 (n.)；給…定價 (v.)",
        "answer": "price"
    },
    {
        "question": "印刷；出版；發行 (v.)",
        "answer": "print"
    },
    {
        "question": "問題；疑難問題 (n.)",
        "answer": "problem"
    },
    {
        "question": "證明；證實 (v.)",
        "answer": "prove"
    },
    {
        "question": "公眾的；政府的 (adj.)；民眾 (n.)",
        "answer": "public"
    },
    {
        "question": "拉；拖 (v.)",
        "answer": "pull"
    },
    {
        "question": "目的；意圖 (n.)",
        "answer": "purpose"
    },
    {
        "question": "推；推進；擴展 (v.)",
        "answer": "push"
    },
    {
        "question": "放；擺；裝 (v.)",
        "answer": "put"
    },
    {
        "question": "女王；王后 (n.)",
        "answer": "queen"
    },
    {
        "question": "問題；詢問 (n.)；詢問 (v.)",
        "answer": "question"
    }
]