[
    {
        "question": "山谷；溪谷 (n.)",
        "answer": "valley"
    },
    {
        "question": "重要性；益處 (n.)",
        "answer": "value"
    },
    {
        "question": "勝利；戰勝；成功 (n.)",
        "answer": "victory"
    },
    {
        "question": "錄影；錄影節目 (n.)",
        "answer": "video"
    },
    {
        "question": "村莊；村民 (n.)",
        "answer": "village"
    },
    {
        "question": "小提琴 (n.)",
        "answer": "violin"
    },
    {
        "question": "訪問者；留住客；探病者 (n.)",
        "answer": "visitor"
    },
    {
        "question": "字彙；語彙 (n.)",
        "answer": "vocabulary"
    },
    {
        "question": "排球；排球運動 (n.)",
        "answer": "volleyball"
    },
    {
        "question": "選舉；投票；表決 (n.)",
        "answer": "vote"
    },
    {
        "question": "選舉人；投票人 (n.)",
        "answer": "voter"
    },
    {
        "question": "腰；腰部 (n.)",
        "answer": "waist"
    },
    {
        "question": "侍者；服務生 (n.)",
        "answer": "waiter"
    },
    {
        "question": "女服務生；女侍應生 (n.)",
        "answer": "waitress"
    },
    {
        "question": "醒來；醒著 (v.)",
        "answer": "wake"
    },
    {
        "question": "皮夾子；錢包 (n.)",
        "answer": "wallet"
    },
    {
        "question": "瀑布 (n.)",
        "answer": "waterfall"
    },
    {
        "question": "西瓜 (n.)",
        "answer": "watermelon"
    },
    {
        "question": "波浪 (n.) / 對...揮手 (v.)",
        "answer": "wave"
    },
    {
        "question": "武器；兵器；兇器 (n.)",
        "answer": "weapon"
    },
    {
        "question": "娶；嫁；與...結婚 (v.)",
        "answer": "wed"
    },
    {
        "question": "平日；工作日 (n.)",
        "answer": "weekday"
    },
    {
        "question": "西方的；西部的 (adj.)",
        "answer": "western"
    },
    {
        "question": "潮濕的；多雨的 (adj.)",
        "answer": "wet"
    },
    {
        "question": "鞭打；揍；猛擊 (v.)",
        "answer": "whale"
    },
    {
        "question": "任何...的事物 (pron.)",
        "answer": "whatever"
    },
    {
        "question": "輪子；方向盤 (n.)",
        "answer": "wheel"
    },
    {
        "question": "無論什麼時候 (adv.)",
        "answer": "whenever"
    },
    {
        "question": "無論在哪裡；無論什麼地方 (conj.)",
        "answer": "wherever"
    },
    {
        "question": "耳語；私語 (v.)",
        "answer": "whisper"
    },
    {
        "question": "放寬；加寬；擴大 (v.)",
        "answer": "widen"
    },
    {
        "question": "誰；無論誰 (pron.)",
        "answer": "whoever"
    },
    {
        "question": "寬度；闊度；寬闊 (n.)",
        "answer": "width"
    },
    {
        "question": "野生的；猛烈的；瘋狂的 (adj.)",
        "answer": "wild"
    },
    {
        "question": "願意的；樂意的 (adj.)",
        "answer": "willing"
    },
    {
        "question": "刮風的；多風的 (adj.)",
        "answer": "windy"
    },
    {
        "question": "翅膀 (n.) / 飛行 (v.)",
        "answer": "wing"
    },
    {
        "question": "獲勝者；優勝者 (n.)",
        "answer": "winner"
    },
    {
        "question": "金屬線；金屬絲；電話線 (n.)",
        "answer": "wire"
    },
    {
        "question": "有智慧的；聰明的；博學的 (adj.)",
        "answer": "wise"
    },
    {
        "question": "在...範圍內；不超過 (prep.)",
        "answer": "within"
    },
    {
        "question": "無；沒有；不 (prep.)",
        "answer": "without"
    },
    {
        "question": "狼 (n.)",
        "answer": "wolf"
    },
    {
        "question": "不明白；驚奇 (v.)",
        "answer": "wonder"
    },
    {
        "question": "極好的；精彩的 (adj.)",
        "answer": "wonderful"
    },
    {
        "question": "木製的；僵硬的；笨拙的 (adj.)",
        "answer": "wooden"
    },
    {
        "question": "羊毛；毛織品 (n.)",
        "answer": "wool"
    },
    {
        "question": "有...的價值 (adj.) / 價值 (n.)",
        "answer": "worth"
    },
    {
        "question": "創傷；傷疤 (n.)",
        "answer": "wound"
    },
    {
        "question": "院子；天井；庭院 (n.)",
        "answer": "yard"
    },
    {
        "question": "青春時代；青年 (n.)",
        "answer": "youth"
    },
    {
        "question": "斑馬 (n.)",
        "answer": "zebra"
    }
]