[
    {
        "question": "不管；儘管 (prep.)",
        "answer": "despite"
    },
    {
        "question": "破壞；毀滅 (n.)",
        "answer": "destruction"
    },
    {
        "question": "偵探；偵探的 (n./adj.)",
        "answer": "detective"
    },
    {
        "question": "堅定；果斷 (n.)",
        "answer": "determination"
    },
    {
        "question": "設備；儀器 (n.)",
        "answer": "device"
    },
    {
        "question": "設計；發明 (v.)",
        "answer": "devise"
    },
    {
        "question": "將...奉獻 (v.)",
        "answer": "devote"
    },
    {
        "question": "尿布 (n.)",
        "answer": "diaper"
    },
    {
        "question": "不同；相異 (v.)",
        "answer": "differ"
    },
    {
        "question": "消化 (v.)",
        "answer": "digest"
    },
    {
        "question": "消化；消化作用 (n.)",
        "answer": "digestion"
    },
    {
        "question": "指的；指狀的；數位的 (adj.)",
        "answer": "digital"
    },
    {
        "question": "尊嚴；莊嚴 (n.)",
        "answer": "dignity"
    },
    {
        "question": "勤勉；勤奮 (n.)",
        "answer": "diligence"
    },
    {
        "question": "外交官 (n.)",
        "answer": "diplomat"
    },
    {
        "question": "畢業文憑；學位證書 (n.)",
        "answer": "diploma"
    },
    {
        "question": "不利條件 (n.)",
        "answer": "disadvantage"
    },
    {
        "question": "災害；災難 (n.)",
        "answer": "disaster"
    },
    {
        "question": "紀律 (n.)",
        "answer": "discipline"
    },
    {
        "question": "使分離；分開 (v.)",
        "answer": "disconnect"
    },
    {
        "question": "使洩氣；使沮喪 (v.)",
        "answer": "discourage"
    },
    {
        "question": "沮喪；氣餒 (n.)",
        "answer": "discouragement"
    },
    {
        "question": "假扮；偽裝 (n.)",
        "answer": "disguise"
    },
    {
        "question": "讓...離開 (v.)",
        "answer": "dismiss"
    },
    {
        "question": "混亂；無秩序 (n.)",
        "answer": "disorder"
    },
    {
        "question": "爭論；爭執 (v.)",
        "answer": "dispute"
    },
    {
        "question": "與其他不同的；有區別的 (adj.)",
        "answer": "distinct"
    },
    {
        "question": "區別；識別 (v.)",
        "answer": "distinguish"
    },
    {
        "question": "卓越的；著名的 (adj.)",
        "answer": "distinguished"
    },
    {
        "question": "分發；分配 (v.)",
        "answer": "distribute"
    },
    {
        "question": "分發；分配 (n.)",
        "answer": "distribution"
    },
    {
        "question": "地區；區域 (n.)",
        "answer": "district"
    },
    {
        "question": "妨礙；打擾 (v.)",
        "answer": "disturb"
    },
    {
        "question": "神授的；天賜的 (adj.)",
        "answer": "divine"
    },
    {
        "question": "離婚 (n.)",
        "answer": "divorce"
    },
    {
        "question": "佔優勢的；支配的 (adj.)",
        "answer": "dominant"
    },
    {
        "question": "學生宿舍 (n.)",
        "answer": "dormitory"
    },
    {
        "question": "宿舍 (n.)",
        "answer": "dorm"
    },
    {
        "question": "下載 (v.)",
        "answer": "download"
    },
    {
        "question": "打瞌睡 (v.)",
        "answer": "doze"
    },
    {
        "question": "草稿；草圖 (n.)",
        "answer": "draft"
    },
    {
        "question": "懼怕；擔心 (v.)",
        "answer": "dread"
    },
    {
        "question": "漂；漂流 (v.)",
        "answer": "drift"
    },
    {
        "question": "操練；訓練 (n.)",
        "answer": "drill"
    },
    {
        "question": "經久的；耐用的 (adj.)",
        "answer": "durable"
    },
    {
        "question": "滿是灰塵的 (adj.)",
        "answer": "dusty"
    },
    {
        "question": "數位視訊影碟 (abbr.)",
        "answer": "DVD (digital video disc)"
    },
    {
        "question": "染料；染色 (n.)",
        "answer": "dye"
    },
    {
        "question": "有動力的；有活力的 (adj.)",
        "answer": "dynamic"
    },
    {
        "question": "王朝；朝代 (n.)",
        "answer": "dynasty"
    }
]